[
  {
    "title": "Pancakes",
    "image": "Pancakes.jpg",
    "defaultPortions": 2,
    "tags": ["vegetarisch"],
    "ingredients": [
      "150g Mehl",
      "1 El Zucker",
      "1 Tl Backpulver",
      "2 Eier",
      "Salz",
      "150 ml Milch"
    ],
    "preparation": [
      "Mehl, Zucker, Backpulver, Eier, Salz und Milch in einer Schüssel vermengen.",
      "Jetzt ein wenig Öl in einer Pfanne erhitzen. Dann den Pfannkuchenteig portionsweise (etwa 2 - 3 Esslöffel reichen)\n  hineingeben und zu einem großen, drei Zentimeter dicken Kreis formen.",
      "Bei mittlerer Hitzestufe wird der Teig nun so lange gebraten, bis die untere Seite golden und braun ist.",
      "Anschließend ein Mal wenden, bis er goldbraun gebraten ist.",
      "Servieren mit z.B. Nutella, Puderzucker"
    ]
  },
  {
    "title": "Milchreis (kalorienarm)",
    "image": "Milchreis.jpg",
    "defaultPortions": 2,
    "tags": ["vegetarisch"],
    "ingredients":[
      "200g Milchreis/Risottoreis",
      "750ml Milch",
      "6 EL Erythrit",
      "Salz"
    ],
    "preparation": [
      "Die Milch in einen Topf erhitzen bis sie anfängt zu schäumen.",
      "Währenddessen den Reis gut waschen und Beiseitestellen.",
      "Wenn die Milch anfängt zu schäumen, den Herd auf niedrige Hitze stellen und den Reis einmischen.",
      "Immer Mal den Reis umrühren und das ganze für 20-30 Minuten kochen lassen.",
      "Am Ende den Milchreis mit Erythrit süßen und eine Prise Salz untermischen."
    ]
  }
]